alignak_module_nrpe_booster/__init__.py
alignak_module_nrpe_booster/nrpe_booster.py
alignak_module_nrpe_booster/etc/__init__.py
alignak_module_nrpe_booster/etc/alignak.d/alignak-module-nrpe-booster.ini
alignak_module_nrpe_booster/etc/arbiter/modules/mod-nrpe-booster.cfg
alignak_module_nrpe_booster-2.1.1.data/data/share/alignak/etc/alignak.d/alignak-module-nrpe-booster.ini
alignak_module_nrpe_booster-2.1.1.data/data/share/alignak/etc/arbiter/modules/mod-nrpe-booster.cfg
test/__init__.py
test/alignak_test.py
test/test_errors.py
test/test_module.py
test/test_simple.py
alignak_module_nrpe_booster-2.1.1.dist-info/AUTHORS
alignak_module_nrpe_booster-2.1.1.dist-info/LICENSE
alignak_module_nrpe_booster-2.1.1.dist-info/METADATA
alignak_module_nrpe_booster-2.1.1.dist-info/WHEEL
alignak_module_nrpe_booster-2.1.1.dist-info/top_level.txt
alignak_module_nrpe_booster-2.1.1.dist-info/RECORD
