Metadata-Version: 2.1
Name: alignak-module-nrpe-booster
Version: 2.1.1
Summary: Alignak - Poller module to boost NRPE checks
Home-page: https://github.com/Alignak-monitoring-contrib/alignak-modules-nrpe-booster
Author: Frédéric Mohier
Author-email: frederic.mohier@alignak.net
License: GNU Affero General Public License, version 3
Keywords: alignak monitoring module checks
Platform: UNKNOWN
Classifier: Development Status :: 5 - Production/Stable
Classifier: Environment :: Console
Classifier: Intended Audience :: Developers
Classifier: Intended Audience :: System Administrators
Classifier: License :: OSI Approved :: GNU Affero General Public License v3 or later (AGPLv3+)
Classifier: Natural Language :: English
Classifier: Programming Language :: Python
Classifier: Topic :: System :: Monitoring
Classifier: Topic :: System :: Systems Administration
Requires-Dist: alignak
